medaipro/__init__.py
medaipro/ai_models.py
medaipro/drugs.py
medaipro/imaging.py
medaipro/report.py
medaipro/signals.py
medaipro/statistics.py
medaipro-1.0.0.dist-info/licenses/LICENSE
medaipro-1.0.0.dist-info/METADATA
medaipro-1.0.0.dist-info/WHEEL
medaipro-1.0.0.dist-info/top_level.txt
medaipro-1.0.0.dist-info/RECORD
