Metadata-Version: 2.4
Name: MedAIPro
Version: 1.0.0
Summary: 世界最先進的醫療人工智慧模組
Author: BSP
Author-email: BSP <your@email.com>
License: MIT License
Project-URL: Homepage, https://github.com/yourname/MedAIPro
Keywords: medical,AI,healthcare,ECG,MRI,AI-model
Requires-Python: >=3.8
License-File: LICENSE
Requires-Dist: numpy
Requires-Dist: pandas
Requires-Dist: opencv-python
Requires-Dist: tensorflow
Requires-Dist: scikit-learn
Requires-Dist: scipy
Requires-Dist: fpdf2
Requires-Dist: joblib
Dynamic: author
Dynamic: license-file
Dynamic: requires-python
